[{"name":"Leather Hat","type":"Hat","rank":1},{"name":"Helm of Darkness","type":"Unique","rank":1},{"name":"Bronze Helm","type":"Helmet","rank":1},{"name":"Feathered Hat","type":"Hat","rank":2},{"name":"Iron Helm","type":"Helmet","rank":2},{"name":"Kanzashi","type":"Hair Accessory","rank":3},{"name":"Knight Helm","type":"Helmet","rank":3},{"name":"Tricorn Cap","type":"Hat","rank":4},{"name":"Extension","type":"Hair Accessory","rank":4},{"name":"Mithril Helm","type":"Helmet","rank":4},{"name":"Green Beret","type":"Hat","rank":4},{"name":"Tiara","type":"Hair Accessory","rank":5},{"name":"Great Helm","type":"Helmet","rank":5},{"name":"Beret","type":"Hat","rank":6},{"name":"Golden Helm","type":"Helmet","rank":6},{"name":"Burgonet","type":"Helmet","rank":6},{"name":"Golden Hairpin","type":"Hair Accessory","rank":7},{"name":"Sallet","type":"Helmet","rank":7},{"name":"Red Cap","type":"Hat","rank":8},{"name":"Diamond Helm","type":"Helmet","rank":8},{"name":"Twist Headband","type":"Hat","rank":9},{"name":"Close-Helm","type":"Helmet","rank":9},{"name":"Rubicant Cowl","type":"Hat","rank":10},{"name":"Lamia Tiara","type":"Hair Accessory","rank":10},{"name":"Crystal Helm","type":"Helmet","rank":10},{"name":"Cat-Earred Hood","type":"Hair Accessory","rank":11},{"name":"Platinum Helm","type":"Helmet","rank":11},{"name":"Tiger Mask","type":"Hat","rank":12},{"name":"Wyrmhelm","type":"Helmet","rank":12},{"name":"Heike Helm","type":"Helmet","rank":12},{"name":"Thief's Hat","type":"Hat","rank":13},{"name":"Slave Crown","type":"Hair Accessory","rank":13},{"name":"Gigas Helm","type":"Helmet","rank":13},{"name":"Black Cowl","type":"Hat","rank":14},{"name":"Circlet","type":"Hair Accessory","rank":14},{"name":"Kaiser Helm","type":"Helmet","rank":14},{"name":"Dueling Mask","type":"Hat","rank":15},{"name":"Floral Crown","type":"Hair Accessory","rank":15},{"name":"Royal Crown","type":"Hair Accessory","rank":15},{"name":"Grand Helm","type":"Helmet","rank":15},{"name":"Genji Helm","type":"Helmet","rank":15}]
